{"imagePath":"texture.png","SubTexture":[{"y":588,"frameX":-24,"frameHeight":232,"frameY":-38,"width":98,"frameWidth":148,"height":154,"name":"111_body","x":692},{"y":835,"frameX":-28,"frameHeight":187,"frameY":-31,"width":107,"frameWidth":162,"height":124,"name":"baiqishi111_body","x":789},{"y":545,"frameX":0,"frameHeight":86,"frameY":0,"width":92,"frameWidth":93,"height":86,"name":"effect/yxl_yc04","x":804},{"y":197,"frameX":-15,"frameHeight":64,"frameY":0,"width":15,"frameWidth":45,"height":64,"name":"zuoxiaotui_body","x":247},{"width":45,"y":197,"height":68,"name":"xiong_body","x":200},{"width":72,"y":507,"height":79,"name":"effect/yxl_qiu_04","x":730},{"width":119,"y":725,"height":119,"name":"effect/yxl_yuan_03","x":331},{"width":208,"y":801,"height":72,"name":"effect/yxl_yc02","x":452},{"width":35,"y":124,"height":80,"name":"new003_body","x":859},{"y":295,"frameX":-22,"frameHeight":63,"frameY":0,"width":22,"frameWidth":67,"height":63,"name":"zuodatui_body","x":741},{"y":945,"frameX":-3,"frameHeight":100,"frameY":-1,"width":96,"frameWidth":100,"height":95,"name":"effect/yxl_dg03_05","x":576},{"y":844,"frameX":-3,"frameHeight":100,"frameY":0,"width":97,"frameWidth":100,"height":99,"name":"effect/yxl_dg03_03","x":662},{"y":945,"frameX":-3,"frameHeight":25,"frameY":0,"width":99,"frameWidth":102,"height":25,"name":"effect/cqy_038","x":674},{"y":547,"frameX":-28,"frameHeight":280,"frameY":-50,"width":102,"frameWidth":157,"height":176,"name":"333_body","x":394},{"y":846,"frameX":0,"frameHeight":96,"frameY":0,"width":99,"frameWidth":100,"height":96,"name":"effect/yxl_qiu01","x":319},{"width":72,"y":426,"height":79,"name":"effect/yxl_qiu_05","x":737},{"width":128,"y":665,"height":124,"name":"effect/yxl_yuan_01","x":201},{"y":2,"frameX":-144,"frameHeight":467,"frameY":-143,"width":260,"frameWidth":561,"height":193,"name":"zhengfuqishi1","x":2},{"y":197,"frameX":0,"frameHeight":132,"frameY":0,"width":196,"frameWidth":203,"height":132,"name":"effect/yxl_00003","x":2},{"y":572,"frameX":-7,"frameHeight":121,"frameY":-8,"width":192,"frameWidth":204,"height":105,"name":"effect/yxl02_00001","x":498},{"y":375,"frameX":-10,"frameHeight":91,"frameY":-22,"width":20,"frameWidth":41,"height":45,"name":"zuodabi_body","x":196},{"y":380,"frameX":-16,"frameHeight":67,"frameY":-16,"width":30,"frameWidth":62,"height":33,"name":"tou_body","x":218},{"y":387,"frameX":-41,"frameHeight":20,"frameY":0,"width":41,"frameWidth":124,"height":20,"name":"new006_body","x":851},{"y":337,"frameX":-15,"frameHeight":67,"frameY":-18,"width":30,"frameWidth":60,"height":36,"name":"new009_body","x":196},{"y":388,"frameX":0,"frameHeight":128,"frameY":0,"width":199,"frameWidth":204,"height":128,"name":"effect/yxl_sudx04","x":250},{"y":875,"frameX":-5,"frameHeight":80,"frameY":0,"width":154,"frameWidth":160,"height":80,"name":"effect/cqy_11_002","x":420},{"width":23,"y":235,"height":80,"name":"dayizuo_body","x":830},{"width":160,"y":518,"height":145,"name":"effect/yl_02","x":232},{"y":734,"frameX":-1,"frameHeight":100,"frameY":0,"width":99,"frameWidth":100,"height":99,"name":"effect/yxl_dg03_01","x":792},{"y":181,"frameX":-22,"frameHeight":66,"frameY":0,"width":16,"frameWidth":60,"height":66,"name":"youxiaotui_body","x":786},{"y":181,"frameX":-21,"frameHeight":112,"frameY":0,"width":43,"frameWidth":86,"height":112,"name":"new011_body","x":741},{"y":124,"frameX":-13,"frameHeight":24,"frameY":0,"width":13,"frameWidth":40,"height":24,"name":"zuojiao_body","x":525},{"y":2,"frameX":0,"frameHeight":120,"frameY":0,"width":274,"frameWidth":276,"height":120,"name":"effect/cqy_14_001","x":264},{"y":211,"frameX":-9,"frameHeight":18,"frameY":0,"width":9,"frameWidth":28,"height":18,"name":"youjiao_body","x":525},{"y":385,"frameX":-11,"frameHeight":21,"frameY":0,"width":23,"frameWidth":46,"height":21,"name":"new010_body","x":759},{"y":548,"frameX":-4,"frameHeight":121,"frameY":-8,"width":192,"frameWidth":204,"height":105,"name":"effect/yxl_00001","x":2},{"y":957,"frameX":0,"frameHeight":52,"frameY":-13,"width":92,"frameWidth":92,"height":25,"name":"zuobi_body","x":402},{"width":228,"y":462,"height":84,"name":"effect/yxl_yc03","x":2},{"width":24,"y":235,"height":83,"name":"dayiyouce_body","x":804},{"y":353,"frameX":0,"frameHeight":33,"frameY":-1,"width":36,"frameWidth":36,"height":32,"name":"yao_body","x":851},{"width":37,"y":366,"height":28,"name":"tun_body","x":812},{"y":331,"frameX":-12,"frameHeight":129,"frameY":0,"width":192,"frameWidth":204,"height":129,"name":"effect/yxl02_00002","x":2},{"y":354,"frameX":-18,"frameHeight":29,"frameY":0,"width":18,"frameWidth":55,"height":29,"name":"555_body","x":765},{"y":315,"frameX":-12,"frameHeight":32,"frameY":-8,"width":12,"frameWidth":38,"height":16,"name":"zuoshou_body","x":246},{"y":380,"frameX":-12,"frameHeight":65,"frameY":-16,"width":25,"frameWidth":51,"height":32,"name":"new004_body","x":785},{"y":827,"frameX":-4,"frameHeight":80,"frameY":0,"width":156,"frameWidth":160,"height":80,"name":"effect/cqy_11_001","x":2},{"y":744,"frameX":-1,"frameHeight":100,"frameY":0,"width":99,"frameWidth":100,"height":98,"name":"effect/yxl_dg03_02","x":688},{"y":192,"frameX":-10,"frameHeight":35,"frameY":-8,"width":10,"frameWidth":31,"height":17,"name":"quantou_body","x":525},{"width":72,"y":466,"height":79,"name":"effect/yxl_qiu_03","x":451},{"width":29,"y":206,"height":83,"name":"dayizuoce_body","x":859},{"width":13,"y":150,"height":18,"name":"bozi_body","x":525},{"y":2,"frameX":-1,"frameHeight":120,"frameY":0,"width":78,"frameWidth":80,"height":120,"name":"effect/yxl_heiying","x":810},{"y":2,"frameX":0,"frameHeight":111,"frameY":0,"width":268,"frameWidth":270,"height":111,"name":"effect/cqy_14_002","x":540},{"y":124,"frameX":-3,"frameHeight":128,"frameY":0,"width":201,"frameWidth":204,"height":128,"name":"effect/yxl02_00005","x":264},{"y":124,"frameX":-24,"frameHeight":109,"frameY":0,"width":49,"frameWidth":99,"height":109,"name":"new013_body","x":808},{"y":422,"frameX":-12,"frameHeight":51,"frameY":-12,"width":50,"frameWidth":76,"height":25,"name":"paobushou_body","x":196},{"y":633,"frameX":-1,"frameHeight":100,"frameY":0,"width":99,"frameWidth":100,"height":99,"name":"effect/yxl_dg03_00","x":792},{"y":249,"frameX":-14,"frameHeight":44,"frameY":0,"width":14,"frameWidth":43,"height":44,"name":"youdabi_body","x":786},{"y":311,"frameX":0,"frameHeight":128,"frameY":0,"width":199,"frameWidth":204,"height":128,"name":"effect/yxl_00004","x":536},{"y":441,"frameX":0,"frameHeight":129,"frameY":0,"width":192,"frameWidth":204,"height":129,"name":"effect/yxl_00002","x":536},{"width":15,"y":263,"height":33,"name":"goupai_body","x":247},{"y":909,"frameX":-7,"frameHeight":80,"frameY":0,"width":152,"frameWidth":160,"height":80,"name":"effect/cqy_11_000","x":2},{"y":267,"frameX":0,"frameHeight":68,"frameY":0,"width":26,"frameWidth":28,"height":68,"name":"dayiyouxia_body","x":200},{"width":121,"y":679,"height":120,"name":"effect/yxl_yuan_04","x":498},{"y":238,"frameX":-16,"frameHeight":97,"frameY":-16,"width":68,"frameWidth":103,"height":64,"name":"new001_body","x":467},{"width":195,"y":748,"height":77,"name":"effect/yxl_yc01","x":2},{"y":911,"frameX":-14,"frameHeight":80,"frameY":0,"width":145,"frameWidth":160,"height":80,"name":"effect/cqy_11_003","x":156},{"y":655,"frameX":-2,"frameHeight":91,"frameY":0,"width":197,"frameWidth":201,"height":91,"name":"effect/cqy_14_000","x":2},{"width":56,"y":409,"height":53,"name":"effect/yxl_yuan02_01","x":841},{"y":115,"frameX":0,"frameHeight":64,"frameY":0,"width":266,"frameWidth":268,"height":64,"name":"effect/cqy_14_003","x":540},{"y":181,"frameX":0,"frameHeight":128,"frameY":0,"width":201,"frameWidth":204,"height":128,"name":"effect/yxl_00005","x":538},{"y":267,"frameX":-4,"frameHeight":36,"frameY":0,"width":17,"frameWidth":25,"height":36,"name":"new005_body","x":228},{"y":333,"frameX":-12,"frameHeight":92,"frameY":-23,"width":25,"frameWidth":51,"height":45,"name":"zuodabi111_body","x":228},{"width":72,"y":385,"height":79,"name":"effect/yxl_qiu_01","x":462},{"y":305,"frameX":-8,"frameHeight":33,"frameY":-8,"width":16,"frameWidth":33,"height":16,"name":"new008_body","x":228},{"width":65,"y":679,"height":65,"name":"effect/yxl_yuan03_01","x":621},{"y":254,"frameX":-7,"frameHeight":132,"frameY":0,"width":196,"frameWidth":203,"height":132,"name":"effect/yxl02_00003","x":264},{"y":396,"frameX":-13,"frameHeight":65,"frameY":-16,"width":27,"frameWidth":54,"height":32,"name":"touqqq_body","x":812},{"width":25,"y":291,"height":60,"name":"dayizuoxia_body","x":855},{"y":944,"frameX":-3,"frameHeight":100,"frameY":0,"width":97,"frameWidth":100,"height":97,"name":"effect/yxl_dg03_04","x":303},{"width":118,"y":791,"height":118,"name":"effect/yxl_yuan_02","x":199},{"width":15,"y":298,"height":15,"name":"new007_body","x":247},{"width":56,"y":124,"height":112,"name":"new002_body","x":467},{"y":170,"frameX":-11,"frameHeight":40,"frameY":-9,"width":11,"frameWidth":33,"height":20,"name":"youshou_body","x":525},{"y":295,"frameX":-16,"frameHeight":43,"frameY":-10,"width":16,"frameWidth":48,"height":21,"name":"shangshou_body","x":786},{"y":360,"frameX":-20,"frameHeight":45,"frameY":0,"width":20,"frameWidth":60,"height":45,"name":"zuoxiabi_body","x":737},{"width":72,"y":304,"height":79,"name":"effect/yxl_qiu_02","x":462},{"y":317,"frameX":-19,"frameHeight":47,"frameY":0,"width":19,"frameWidth":57,"height":47,"name":"youxiabi_body","x":830},{"y":320,"frameX":0,"frameHeight":60,"frameY":0,"width":24,"frameWidth":27,"height":58,"name":"dayiyou_body","x":786},{"y":295,"frameX":-20,"frameHeight":57,"frameY":0,"width":19,"frameWidth":60,"height":57,"name":"youdatui_body","x":765},{"y":291,"frameX":-16,"frameHeight":33,"frameY":0,"width":16,"frameWidth":48,"height":33,"name":"222_body","x":882},{"y":408,"frameX":-16,"frameHeight":16,"frameY":0,"width":32,"frameWidth":64,"height":16,"name":"new012_body","x":737},{"width":72,"y":464,"height":79,"name":"effect/yxl_qiu_00","x":811}],"name":"baiqishi"}